dynamic_cfg/__init__.py
dynamic_cfg/_modidx.py
dynamic_cfg/core.py
dynamic_cfg/diffusion.py
dynamic_cfg/guidance.py
dynamic_cfg/kdiff.py
dynamic_cfg/normalizers.py
dynamic_cfg/schedules.py
dynamic_cfg/transforms.py
dynamic_cfg/utils.py
dynamic_cfg-0.0.1.dist-info/LICENSE
dynamic_cfg-0.0.1.dist-info/METADATA
dynamic_cfg-0.0.1.dist-info/WHEEL
dynamic_cfg-0.0.1.dist-info/entry_points.txt
dynamic_cfg-0.0.1.dist-info/top_level.txt
dynamic_cfg-0.0.1.dist-info/RECORD
