Metadata-Version: 2.1
Name: dynamic-cfg
Version: 0.0.1
Summary: dynamic Classifier-free Guidance for Diffusion models
Home-page: https://github.com/enzokro/dynamic_cfg
Author: enzokro
Author-email: christopher.kroenke@gmail.com
License: Apache Software License 2.0
Keywords: nbdev jupyter notebook python
Classifier: Development Status :: 4 - Beta
Classifier: Intended Audience :: Developers
Classifier: Natural Language :: English
Classifier: Programming Language :: Python :: 3.8
Classifier: Programming Language :: Python :: 3.9
Classifier: Programming Language :: Python :: 3.10
Classifier: License :: OSI Approved :: Apache Software License
Requires-Python: >=3.8
License-File: LICENSE
Requires-Dist: torch (>=1.7)
Requires-Dist: transformers
Requires-Dist: diffusers
Requires-Dist: tqdm
Requires-Dist: numpy
Requires-Dist: matplotlib
Provides-Extra: dev
